{"cameraMode":{"drawMode":0,"name":"Shaded","section":"Shading Mode"},"sceneLighting":true,"audioPlay":false,"sceneViewState":{"m_AlwaysRefresh":false,"showFog":true,"showSkybox":true,"showFlares":true,"showImageEffects":true,"showParticleSystems":true,"showVisualEffectGraphs":true,"m_FxEnabled":true},"in2DMode":false,"pivot":{"x":-2.8157567977905275,"y":4.469946384429932,"z":0.3001828193664551},"rotation":{"x":0.024235181510448457,"y":-0.9702054262161255,"z":0.10962001234292984,"w":0.21483507752418519},"size":1.4980823993682862,"orthographic":false}